AUTHORS
LICENSE
MANIFEST.in
README.rst
setup.py
django_oml.egg-info/PKG-INFO
django_oml.egg-info/SOURCES.txt
django_oml.egg-info/dependency_links.txt
django_oml.egg-info/not-zip-safe
django_oml.egg-info/top_level.txt
oml/__init__.py
oml/managers.py
oml/models.py
oml/tests.py
oml/views.py