Metadata-Version: 1.1
Name: django-oml
Version: 0.0.1
Summary: An app that allows you moderate content
Home-page: http://www.routeatlas.com
Author: Angel Velasquez, Agustín Cangiani
Author-email: angvp@archlinux.org, cangiani@gmail.com
License: GPL
Platform: UNKNOWN
Classifier: Topic :: Internet :: WWW/HTTP :: Dynamic Content
Classifier: Intended Audience :: Developers
Classifier: Programming Language :: Python
Classifier: Programming Language :: Python :: 2.6
Classifier: Programming Language :: Python :: 2.7
Classifier: Framework :: Django
Classifier: Development Status :: 4 - Beta
Classifier: Operating System :: OS Independent
